stripe_agent_toolkit/__init__.py
stripe_agent_toolkit/api.py
stripe_agent_toolkit/configuration.py
stripe_agent_toolkit/functions.py
stripe_agent_toolkit/prompts.py
stripe_agent_toolkit/schema.py
stripe_agent_toolkit/tools.py
stripe_agent_toolkit/crewai/tool.py
stripe_agent_toolkit/crewai/toolkit.py
stripe_agent_toolkit/langchain/tool.py
stripe_agent_toolkit/langchain/toolkit.py
stripe_agent_toolkit/openai/hooks.py
stripe_agent_toolkit/openai/tool.py
stripe_agent_toolkit/openai/toolkit.py
stripe_agent_toolkit-0.6.1.dist-info/licenses/LICENSE
stripe_agent_toolkit-0.6.1.dist-info/METADATA
stripe_agent_toolkit-0.6.1.dist-info/WHEEL
stripe_agent_toolkit-0.6.1.dist-info/top_level.txt
stripe_agent_toolkit-0.6.1.dist-info/RECORD
