Metadata-Version: 2.4
Name: stripe-agent-toolkit
Version: 0.6.1
Summary: Stripe Agent Toolkit
Author-email: Stripe <support@stripe.com>
License: The MIT License (MIT)
Project-URL: Bug Tracker, https://github.com/stripe/agent-toolkit/issues
Project-URL: Source Code, https://github.com/stripe/agent-toolkit
Keywords: stripe,api,payments
License-File: LICENSE
Dynamic: license-file
